pykma_grid/__init__.py
pykma_grid/coordinate.py
pykma_grid-1.0.0.dist-info/METADATA
pykma_grid-1.0.0.dist-info/WHEEL
pykma_grid-1.0.0.dist-info/top_level.txt
pykma_grid-1.0.0.dist-info/RECORD
