Metadata-Version: 2.1
Name: pykma-grid
Version: 1.0.0
Summary: A Python package for converting latitude and longitude to grid coordinates using Lambert Conformal Conic Projection
Home-page: https://github.com/gaon12/pykma_grid
Author: Jeong Gaon
Author-email: gokirito12@gmail.com
License: UNKNOWN
Platform: UNKNOWN
Classifier: Programming Language :: Python :: 3
Classifier: License :: OSI Approved :: MIT License
Classifier: Operating System :: OS Independent
Requires-Python: >=3.6
